CTFAssistant/__init__.py
CTFAssistant/main.py
CTFAssistant-0.0.1.dist-info/METADATA
CTFAssistant-0.0.1.dist-info/WHEEL
CTFAssistant-0.0.1.dist-info/top_level.txt
CTFAssistant-0.0.1.dist-info/RECORD
