Metadata-Version: 2.1
Name: CTFAssistant
Version: 0.0.1
Summary: 青少年CTF的Python库模块
Home-page: https://github.com/Moxin1044/qsnctf-python
Author: Moxin
Author-email: 1044631097@qq.com
License: MIT License
